app.py
python_todo/__init__.py
python_todo/components/__init__.py
python_todo/components/app_footer_component.py
python_todo/components/app_header_component.py
python_todo/components/error_message.py
python_todo/components/login_form_component.py
python_todo/components/todo_item_component.py
python_todo/components/todo_list_component.py
python_todo/db.py
python_todo/modals/__init__.py
python_todo/modals/add_todo_modal.py
python_todo/modals/change_password_modal.py
python_todo/modals/change_username_modal.py
python_todo/modals/error_modal.py
python_todo/modals/todo_detail_modal.py
python_todo/models.py
python_todo/screens/__init__.py
python_todo/screens/login_screen.py
python_todo/screens/main_screen.py
python_todo/security.py
pycmd_todo-0.1.3.dist-info/LICENSE
pycmd_todo-0.1.3.dist-info/METADATA
pycmd_todo-0.1.3.dist-info/WHEEL
pycmd_todo-0.1.3.dist-info/entry_points.txt
pycmd_todo-0.1.3.dist-info/RECORD
